{"_type":"export","__export_format":4,"__export_date":"2025-01-07T20:42:15.274Z","__export_source":"insomnia.desktop.app:v10.2.0","resources":[{"_id":"req_59745862647d4ceb860cb5a4646fc4d0","parentId":"wrk_34a7238040a2467fa9b435fdb3ccd501","modified":1736282523174,"created":1736263359952,"url":"http://127.0.0.1:8000/api/token-auth/","name":"Request de Token","description":"","method":"POST","body":{"mimeType":"application/json","text":"{\n    \"username\": \"admin\",\n    \"password\": \"adminadmin\"\n}"},"parameters":[],"headers":[{"name":"Content-Type","value":"application/json","id":"pair_bab0198d4abb470f804cdbe216b0332a"},{"name":"User-Agent","value":"insomnia/10.2.0","id":"pair_5ff7006bb7914f4cba94f4e26dcadea2"},{"id":"pair_79e282b6d2fe4c8e89dd7cf26ebd32b5","name":"Authorization","value":"Token 161c6cb1e2507a9073840b1b740bab3c6c1640c6","description":"","disabled":false}],"authentication":{"type":"bearer","token":"161c6cb1e2507a9073840b1b740bab3c6c1640c6","disabled":true},"metaSortKey":-1736263359952,"isPrivate":false,"pathParameters":[],"settingStoreCookies":true,"settingSendCookies":true,"settingDisableRenderRequestBody":false,"settingEncodeUrl":true,"settingRebuildPath":true,"settingFollowRedirects":"global","_type":"request"},{"_id":"wrk_34a7238040a2467fa9b435fdb3ccd501","parentId":null,"modified":1736262509009,"created":1736262509009,"name":"my-spec.yaml","description":"","scope":"design","_type":"workspace"},{"_id":"req_c5361ebfb8ec47d894242a0dfe22ce2e","parentId":"fld_e03e1ca101c84d3ab5a4b82959fec784","modified":1733438054783,"created":1733437917416,"url":"http://127.0.0.1:8000/users/","name":"Deletar Usuários","description":"","method":"DELETE","body":{},"parameters":[],"headers":[{"name":"User-Agent","value":"insomnia/10.2.0"}],"authentication":{},"metaSortKey":-1733437917416,"isPrivate":false,"pathParameters":[],"settingStoreCookies":true,"settingSendCookies":true,"settingDisableRenderRequestBody":false,"settingEncodeUrl":true,"settingRebuildPath":true,"settingFollowRedirects":"global","_type":"request"},{"_id":"fld_e03e1ca101c84d3ab5a4b82959fec784","parentId":"wrk_34a7238040a2467fa9b435fdb3ccd501","modified":1733437825127,"created":1733437825127,"name":"Usuários","description":"","environment":{},"environmentPropertyOrder":null,"metaSortKey":-1733437825127,"environmentType":"kv","_type":"request_group"},{"_id":"req_c6009c7d1acb4366a8ef29a6f840d413","parentId":"fld_e03e1ca101c84d3ab5a4b82959fec784","modified":1736267764818,"created":1733437896374,"url":"{{ _.api_url }}gerentes/1/","name":"Atualizar Usuários Parcial","description":"","method":"PATCH","body":{"mimeType":"application/json","text":"{\n  \"funcao\": \"testador\"\n}"},"parameters":[],"headers":[{"name":"Content-Type","value":"application/json","id":"pair_eced1897febe4cc4a101f384807c063e"},{"name":"User-Agent","value":"insomnia/10.2.0","id":"pair_2085b0adca13479288dd781e927a622a"},{"id":"pair_210b309ad19f4eb0b732db553384f629","name":"Authorization","value":"Token 161c6cb1e2507a9073840b1b740bab3c6c1640c6","description":"","disabled":false}],"authentication":{},"metaSortKey":-1733437896374,"isPrivate":false,"pathParameters":[],"settingStoreCookies":true,"settingSendCookies":true,"settingDisableRenderRequestBody":false,"settingEncodeUrl":true,"settingRebuildPath":true,"settingFollowRedirects":"global","_type":"request"},{"_id":"req_9d5cf7bc90844841b7c8a159a466f29f","parentId":"fld_e03e1ca101c84d3ab5a4b82959fec784","modified":1736267759111,"created":1733437883485,"url":"{{ _.api_url }}gerentes/2/","name":"Atualizar Usuários","description":"","method":"PUT","body":{"mimeType":"application/json","text":"{\n\t\"nome\": \n\t\t\"Teste\"\n\t,\n\t\"funcao\": \n\t\t\"Gerente\"\n\t,\n\t\"isGerente\": \n\t\t\"true\"\n\t,\n\t\"user\": \n\t\t1\n}"},"parameters":[],"headers":[{"name":"Content-Type","value":"application/json","id":"pair_a5809633376a494b9eecbecd18d0fc4d"},{"name":"User-Agent","value":"insomnia/10.2.0","id":"pair_8f7ec6d0b206494c8480d93dcf48756b"},{"id":"pair_241c4069d8354888930b382484d29ee4","name":"Authorization","value":"Token 161c6cb1e2507a9073840b1b740bab3c6c1640c6","description":"","disabled":false}],"authentication":{},"metaSortKey":-1733437883485,"isPrivate":false,"pathParameters":[],"settingStoreCookies":true,"settingSendCookies":true,"settingDisableRenderRequestBody":false,"settingEncodeUrl":true,"settingRebuildPath":true,"settingFollowRedirects":"global","_type":"request"},{"_id":"req_b91ff1ec5e054c449cbf44cbf8d6fefd","parentId":"fld_e03e1ca101c84d3ab5a4b82959fec784","modified":1736267753300,"created":1733437868406,"url":"{{ _.api_url }}gerentes/","name":"Cadastrar Usuários","description":"","method":"POST","body":{"mimeType":"application/json","text":"{\n    \"nome\": \"Jão\",\n    \"funcao\": \"Gerente Financeiro\",\n    \"isGerente\": true,\n\t\t\"user\": 7,\n    \"login\": \"maria.oliveira\",\n    \"senha\": \"seguranca123\"\n}\n"},"parameters":[],"headers":[{"name":"Content-Type","value":"application/json","id":"pair_c1c6ee65978e43c7ab630ff7ef6780b9"},{"name":"User-Agent","value":"insomnia/10.2.0","id":"pair_d8421280edbd495799ed12b644a3a68d"},{"id":"pair_b0325b0267174b599f1eb9c132c5ea40","name":"Authorization","value":"Token 161c6cb1e2507a9073840b1b740bab3c6c1640c6","description":"","disabled":false}],"authentication":{},"metaSortKey":-1733437868406,"isPrivate":false,"pathParameters":[],"settingStoreCookies":true,"settingSendCookies":true,"settingDisableRenderRequestBody":false,"settingEncodeUrl":true,"settingRebuildPath":true,"settingFollowRedirects":"global","_type":"request"},{"_id":"req_877ae144f6ec4459b8e4aea050024203","parentId":"fld_e03e1ca101c84d3ab5a4b82959fec784","modified":1736266381337,"created":1733437829044,"url":"{{ _.api_url }}gerentes/","name":"Listar Usuários","description":"","method":"GET","body":{"mimeType":"application/json","text":""},"parameters":[],"headers":[{"name":"Content-Type","value":"application/json","id":"pair_ed5315e3186047bb93154de6f1665ffa"},{"name":"User-Agent","value":"insomnia/10.2.0","id":"pair_2d1041633a714fb2974703ed1d71fd08"},{"id":"pair_cbfcba47acc44206abfb36425559062e","name":"Authorization","value":"Token 161c6cb1e2507a9073840b1b740bab3c6c1640c6","description":"","disabled":false}],"authentication":{"type":"bearer","token":"161c6cb1e2507a9073840b1b740bab3c6c1640c6"},"metaSortKey":-1733437829044,"isPrivate":false,"pathParameters":[],"settingStoreCookies":true,"settingSendCookies":true,"settingDisableRenderRequestBody":false,"settingEncodeUrl":true,"settingRebuildPath":true,"settingFollowRedirects":"global","_type":"request"},{"_id":"req_c001aa74a7604e8bbb2d03d8b9bad135","parentId":"fld_6c2724bb6e9c4de2a2cf261564e328e6","modified":1734551292608,"created":1733437644832,"url":"{{ _.api_url }}items/1/","name":"Deletar Item","description":"","method":"DELETE","body":{},"parameters":[],"headers":[{"name":"User-Agent","value":"insomnia/10.2.0"}],"authentication":{},"metaSortKey":-1733437644832,"isPrivate":false,"pathParameters":[],"settingStoreCookies":true,"settingSendCookies":true,"settingDisableRenderRequestBody":false,"settingEncodeUrl":true,"settingRebuildPath":true,"settingFollowRedirects":"global","_type":"request"},{"_id":"fld_6c2724bb6e9c4de2a2cf261564e328e6","parentId":"wrk_34a7238040a2467fa9b435fdb3ccd501","modified":1733437530761,"created":1733437530761,"name":"Itens","description":"","environment":{},"environmentPropertyOrder":null,"metaSortKey":-1733437530761,"environmentType":"kv","_type":"request_group"},{"_id":"req_471961ed37c943a4aef86df9a08c9959","parentId":"fld_6c2724bb6e9c4de2a2cf261564e328e6","modified":1736267790791,"created":1733437629588,"url":"{{ _.api_url }}items/1/","name":"Atualizar Item Parcial","description":"","method":"PATCH","body":{"mimeType":"application/json","text":"{\n\t\"price\": \"900.00\",\n\t\"description\": \"Abacaxi ta MUITO caro\"\n}"},"parameters":[],"headers":[{"name":"Content-Type","value":"application/json","id":"pair_9599f8ce475d41f092c44ce35913e4d6"},{"name":"User-Agent","value":"insomnia/10.2.0","id":"pair_c958a496f45f48369f75fb823480e4f2"},{"id":"pair_00af5ebff351495eb7b05847b5981bcf","name":"Authorization","value":"Token 161c6cb1e2507a9073840b1b740bab3c6c1640c6","description":"","disabled":false}],"authentication":{},"metaSortKey":-1733437629588,"isPrivate":false,"pathParameters":[],"settingStoreCookies":true,"settingSendCookies":true,"settingDisableRenderRequestBody":false,"settingEncodeUrl":true,"settingRebuildPath":true,"settingFollowRedirects":"global","_type":"request"},{"_id":"req_c38a7804e4c34318857a01c8100aa9f9","parentId":"fld_6c2724bb6e9c4de2a2cf261564e328e6","modified":1736267786172,"created":1733437614171,"url":"{{ _.api_url }}items/1/","name":"Atualizar Item","description":"","method":"PUT","body":{"mimeType":"application/json","text":"{\n\t\"name\": \n\t\t\"Abacaxi\"\n\t,\n\t\"price\": \n\t\t\"25.00\"\n\t,\n\t\"description\": \n\t\t\"Abacaxi ta caro\"\n\t,\n\t\"category\": \n\t\t1\n}"},"parameters":[],"headers":[{"name":"Content-Type","value":"application/json","id":"pair_6ad598bffe784e488cbf3adba4ac0873"},{"name":"User-Agent","value":"insomnia/10.2.0","id":"pair_0fccbb15c80e49869364349a65cb43e8"},{"id":"pair_c293c0b0a74d497898683882e7466e94","name":"Authorization","value":"Token 161c6cb1e2507a9073840b1b740bab3c6c1640c6","description":"","disabled":false}],"authentication":{},"metaSortKey":-1733437614171,"isPrivate":false,"pathParameters":[],"settingStoreCookies":true,"settingSendCookies":true,"settingDisableRenderRequestBody":false,"settingEncodeUrl":true,"settingRebuildPath":true,"settingFollowRedirects":"global","_type":"request"},{"_id":"req_93eb46d1ab4f4720b508a8faf09f433c","parentId":"fld_6c2724bb6e9c4de2a2cf261564e328e6","modified":1736267780186,"created":1733437591272,"url":"{{ _.api_url }}items/","name":"Cadastrar Item","description":"","method":"POST","body":{"mimeType":"application/json","text":"{\n\t\"name\": \n\t\t\"Iphone\"\n\t,\n\t\"price\": \n\t\t\"15000\"\n\t,\n\t\"description\": \n\t\t\"celular caro\"\n\t,\n\t\"category\": \n\t\t1\n\t\n}"},"parameters":[],"headers":[{"name":"Content-Type","value":"application/json","id":"pair_6884755f5a8e4c588df09e32630088cf"},{"name":"User-Agent","value":"insomnia/10.2.0","id":"pair_8ef69fb40a54402db79e2fb7aa6c8bf8"},{"id":"pair_8ee4357255b34b6b8721ff69e53cc057","name":"Authorization","value":"Token 161c6cb1e2507a9073840b1b740bab3c6c1640c6","description":"","disabled":false}],"authentication":{},"metaSortKey":-1733437591272,"isPrivate":false,"pathParameters":[],"settingStoreCookies":true,"settingSendCookies":true,"settingDisableRenderRequestBody":false,"settingEncodeUrl":true,"settingRebuildPath":true,"settingFollowRedirects":"global","_type":"request"},{"_id":"req_e53812e6177347acb3e12590acea03f5","parentId":"fld_6c2724bb6e9c4de2a2cf261564e328e6","modified":1736267847010,"created":1733437539862,"url":"{{ _.api_url }}items/","name":"Listar Item","description":"","method":"GET","body":{"mimeType":"application/json","text":"[\n\t{\n\t\t\"id\": 5,\n\t\t\"name\": \"teste\",\n\t\t\"quantity\": 1,\n\t\t\"price\": \"12.00\",\n\t\t\"description\": \"aaaaaa\",\n\t\t\"category\": 10\n\t}\n]"},"parameters":[],"headers":[{"name":"Content-Type","value":"application/json","id":"pair_7d5f4154dbf24b52bb9efd1657ed7896"},{"name":"User-Agent","value":"insomnia/10.2.0","id":"pair_225a2ec5c91c4451aa54e03a0573f0a6"},{"id":"pair_49cb5ca225734786aa58cc4b21dc4e92","name":"Authorization","value":"Token 161c6cb1e2507a9073840b1b740bab3c6c1640c6","description":"","disabled":false}],"authentication":{},"metaSortKey":-1733437539862,"isPrivate":false,"pathParameters":[],"settingStoreCookies":true,"settingSendCookies":true,"settingDisableRenderRequestBody":false,"settingEncodeUrl":true,"settingRebuildPath":true,"settingFollowRedirects":"global","_type":"request"},{"_id":"req_6f98d078dda545d9828b67b102085278","parentId":"fld_0807e3e0886e4591b289bb43b1e55b73","modified":1733437509426,"created":1733429511141,"url":"http://127.0.0.1:8000/categories/","name":"Deletar Categoria","description":"","method":"DELETE","body":{},"parameters":[],"headers":[{"name":"User-Agent","value":"insomnia/10.2.0"}],"authentication":{},"metaSortKey":-1733429511141,"isPrivate":false,"pathParameters":[],"settingStoreCookies":true,"settingSendCookies":true,"settingDisableRenderRequestBody":false,"settingEncodeUrl":true,"settingRebuildPath":true,"settingFollowRedirects":"global","_type":"request"},{"_id":"fld_0807e3e0886e4591b289bb43b1e55b73","parentId":"wrk_34a7238040a2467fa9b435fdb3ccd501","modified":1733429343927,"created":1733429343927,"name":"Categorias","description":"","environment":{},"environmentPropertyOrder":null,"metaSortKey":-1733429343927,"environmentType":"kv","_type":"request_group"},{"_id":"req_8345be7bab784fc2a726bdb840360608","parentId":"fld_0807e3e0886e4591b289bb43b1e55b73","modified":1736267818488,"created":1733429497125,"url":"{{ _.api_url }}categories/4/","name":"Atualizar Categoria Parcial","description":"","method":"PATCH","body":{"mimeType":"application/json","text":"{\n\t\"name\": \n\t\t\"Salada de Frutas Premium\"\n}"},"parameters":[],"headers":[{"name":"Content-Type","value":"application/json","id":"pair_d3445e9920084b85a3f3633bb57586f1"},{"name":"User-Agent","value":"insomnia/10.2.0","id":"pair_34a58eb7e5304406a50f88d9ae7104f9"},{"id":"pair_761f5f3114f64b2e96aa12ed8f566fdd","name":"Authorization","value":"Token 161c6cb1e2507a9073840b1b740bab3c6c1640c6","description":"","disabled":false}],"authentication":{},"metaSortKey":-1733429497125,"isPrivate":false,"pathParameters":[],"settingStoreCookies":true,"settingSendCookies":true,"settingDisableRenderRequestBody":false,"settingEncodeUrl":true,"settingRebuildPath":true,"settingFollowRedirects":"global","_type":"request"},{"_id":"req_f20fe92a296148bf99713581f4a0d6de","parentId":"fld_0807e3e0886e4591b289bb43b1e55b73","modified":1736267810766,"created":1733429440229,"url":"{{ _.api_url }}categories/4/","name":"Atualizar Categoria","description":"","method":"PUT","body":{"mimeType":"application/json","text":"{\n\t\"name\": \n\t\t\"Salada de Frutas\"\n}"},"parameters":[],"headers":[{"name":"Content-Type","value":"application/json","id":"pair_d17d7b6707444592a9eba695e0f98f42"},{"name":"User-Agent","value":"insomnia/10.2.0","id":"pair_1ea844beb5974263afeef5a1132ef983"},{"id":"pair_8373dd970bee441c9767f30056a9eed2","name":"Authorization","value":"Token 161c6cb1e2507a9073840b1b740bab3c6c1640c6","description":"","disabled":false}],"authentication":{},"metaSortKey":-1733429440229,"isPrivate":false,"pathParameters":[],"settingStoreCookies":true,"settingSendCookies":true,"settingDisableRenderRequestBody":false,"settingEncodeUrl":true,"settingRebuildPath":true,"settingFollowRedirects":"global","_type":"request"},{"_id":"req_9d9e42c7d3614167a6c1fd400eedb205","parentId":"fld_0807e3e0886e4591b289bb43b1e55b73","modified":1736267803613,"created":1733429416118,"url":"{{ _.api_url }}categories/","name":"Cadastrar Categoria","description":"","method":"POST","body":{"mimeType":"application/json","text":"{\n\t\"name\": \n\t\t\"Frutas\"\n}"},"parameters":[],"headers":[{"name":"Content-Type","value":"application/json","id":"pair_c0b58441750b4bda9584dcd5c39e8357"},{"name":"User-Agent","value":"insomnia/10.2.0","id":"pair_1edbd86848ef4bbc8f43ed28a253c228"},{"id":"pair_4f212f2026434c96aade235a31260c69","name":"Authorization","value":"Token 161c6cb1e2507a9073840b1b740bab3c6c1640c6","description":"","disabled":false}],"authentication":{},"metaSortKey":-1733429416118,"isPrivate":false,"pathParameters":[],"settingStoreCookies":true,"settingSendCookies":true,"settingDisableRenderRequestBody":false,"settingEncodeUrl":true,"settingRebuildPath":true,"settingFollowRedirects":"global","_type":"request"},{"_id":"req_053445961d5248ebb0b81d7f9bed161a","parentId":"fld_0807e3e0886e4591b289bb43b1e55b73","modified":1736267798537,"created":1733429389378,"url":"{{ _.api_url }}categories/","name":"Listar Categorias","description":"","method":"GET","body":{"mimeType":"application/json","text":"[\n\t{\n\t\t\"id\": 5,\n\t\t\"name\": \"teste\",\n\t\t\"description\": \"testes testados\"\n\t}\n]\n"},"parameters":[],"headers":[{"name":"Content-Type","value":"application/json","id":"pair_edd33ca16a37494e9dd2afa8036de588"},{"name":"User-Agent","value":"insomnia/10.2.0","id":"pair_258e651544764b279839be69fd1f44d0"},{"id":"pair_75b77ffd76da45d885d7029724e68cbc","name":"Authorization","value":"Token 161c6cb1e2507a9073840b1b740bab3c6c1640c6","description":"","disabled":false}],"authentication":{},"metaSortKey":-1733429389378,"isPrivate":false,"pathParameters":[],"settingStoreCookies":true,"settingSendCookies":true,"settingDisableRenderRequestBody":false,"settingEncodeUrl":true,"settingRebuildPath":true,"settingFollowRedirects":"global","_type":"request"},{"_id":"env_1b9c58f98c114c0bbd0a1bbd88af8c26","parentId":"wrk_34a7238040a2467fa9b435fdb3ccd501","modified":1734544010849,"created":1733428587568,"name":"Base Environment","data":{"":""},"dataPropertyOrder":null,"color":null,"isPrivate":false,"metaSortKey":1733428587568,"environmentType":"kv","kvPairData":[{"id":"envPair_502fbc3194384243ab9eb3ca15247691","name":"","value":"","type":"str","enabled":true}],"_type":"environment"},{"_id":"jar_708252120f8e49f1bdb9c2b958aa74fa","parentId":"wrk_34a7238040a2467fa9b435fdb3ccd501","modified":1733429589827,"created":1733428587570,"name":"Default Jar","cookies":[],"_type":"cookie_jar"},{"_id":"spc_f7bc6d5433bd47e88b7e73c894a9f2a1","parentId":"wrk_34a7238040a2467fa9b435fdb3ccd501","modified":1736262509014,"created":1736262509013,"fileName":"my-spec.yaml","contents":"","contentType":"yaml","_type":"api_spec"},{"_id":"uts_8e39f1bdae154503b4f52bdbcd57fe22","parentId":"wrk_34a7238040a2467fa9b435fdb3ccd501","modified":1734034969253,"created":1734024113950,"name":"Suíte de Testes de Usuário","metaSortKey":-1734024135025,"_type":"unit_test_suite"},{"_id":"uts_2a43da46f9f145828b641cd71a9a04be","parentId":"wrk_34a7238040a2467fa9b435fdb3ccd501","modified":1734024155761,"created":1734024135023,"name":"Suíte de Testes de Item","metaSortKey":-1734024135023,"_type":"unit_test_suite"},{"_id":"uts_d0133a28c6db4d8792215b1a0342916e","parentId":"wrk_34a7238040a2467fa9b435fdb3ccd501","modified":1734024172320,"created":1734024155814,"name":"Suíte de Testes de Categoria","metaSortKey":-1734024135022,"_type":"unit_test_suite"},{"_id":"env_9ef10fcb95e14fcf9acb4cd42ef9a47a","parentId":"env_1b9c58f98c114c0bbd0a1bbd88af8c26","modified":1734595234390,"created":1734543906668,"name":"Development","data":{"api_url":"http://127.0.0.1:8000/"},"dataPropertyOrder":null,"color":"#940ac7","isPrivate":false,"metaSortKey":1734543906668,"environmentType":"kv","kvPairData":[{"id":"envPair_d6e73c6a7749427686267d2a9c56f7d7","name":"api_url","value":"http://127.0.0.1:8000/","type":"str","enabled":true}],"_type":"environment"},{"_id":"env_f26d361ba6e14f2197c54c686b187a96","parentId":"env_1b9c58f98c114c0bbd0a1bbd88af8c26","modified":1734595244103,"created":1734543909291,"name":"Homologação","data":{"api_url":"https://danielandrade.pythonanywhere.com/"},"dataPropertyOrder":null,"color":"#0eaf46","isPrivate":false,"metaSortKey":1734543909291,"environmentType":"kv","kvPairData":[{"id":"envPair_5980db05ef384908adb1841595171fa2","name":"api_url","value":"https://danielandrade.pythonanywhere.com/","type":"str","enabled":true}],"_type":"environment"},{"_id":"ut_a60f91c0f59042649cb013828c2e839f","parentId":"uts_8e39f1bdae154503b4f52bdbcd57fe22","modified":1734024401547,"created":1734024274154,"requestId":"req_877ae144f6ec4459b8e4aea050024203","name":"Listagem","code":"const response1 = await insomnia.send();\nexpect(response1.status).to.equal(200);","metaSortKey":-1734024352523.5,"_type":"unit_test"},{"_id":"ut_3d2214baa1894dac85a6af064ada8d01","parentId":"uts_8e39f1bdae154503b4f52bdbcd57fe22","modified":1734034109647,"created":1734024328023,"requestId":"req_c6009c7d1acb4366a8ef29a6f840d413","name":"Atualizar Parcialmente","code":"const response1 = await insomnia.send();\nexpect(response1.status).to.equal(200);","metaSortKey":-1734024352523.375,"_type":"unit_test"},{"_id":"ut_6d06829c8d2648a6bb1b1d0ae7b31924","parentId":"uts_8e39f1bdae154503b4f52bdbcd57fe22","modified":1734035573251,"created":1734024352523,"requestId":"req_9d5cf7bc90844841b7c8a159a466f29f","name":"Atualizar Usuários","code":"const response1 = await insomnia.send();\nexpect(response1.status).to.equal(200);","metaSortKey":-1734024352523,"_type":"unit_test"},{"_id":"ut_b46c41f22ec748cfaaae13bbc3b552b6","parentId":"uts_8e39f1bdae154503b4f52bdbcd57fe22","modified":1734586985893,"created":1734035220952,"requestId":"req_b91ff1ec5e054c449cbf44cbf8d6fefd","name":"Novo Usuário","code":"const response1 = await insomnia.send();\nexpect(response1.status).to.equal(201);","metaSortKey":-1734029786738,"_type":"unit_test"},{"_id":"ut_7830b5087c4947129c8cf286f9b0f6a9","parentId":"uts_2a43da46f9f145828b641cd71a9a04be","modified":1734025167884,"created":1734024428455,"requestId":"req_93eb46d1ab4f4720b508a8faf09f433c","name":"Cadastrar Item","code":"const response1 = await insomnia.send();\nexpect(response1.status).to.equal(201);","metaSortKey":-1734024448164,"_type":"unit_test"},{"_id":"ut_83c01577f85d4baa881e8f38661fb948","parentId":"uts_2a43da46f9f145828b641cd71a9a04be","modified":1734024475904,"created":1734024440202,"requestId":"req_e53812e6177347acb3e12590acea03f5","name":"Listar Item","code":"const response1 = await insomnia.send();\nexpect(response1.status).to.equal(200);","metaSortKey":-1734024448163.5,"_type":"unit_test"},{"_id":"ut_76685e0c33244928a9a67d812a65bdaf","parentId":"uts_2a43da46f9f145828b641cd71a9a04be","modified":1734024483460,"created":1734024444334,"requestId":"req_471961ed37c943a4aef86df9a08c9959","name":"Atualizar Item Parcial","code":"const response1 = await insomnia.send();\nexpect(response1.status).to.equal(200);","metaSortKey":-1734024448163.125,"_type":"unit_test"},{"_id":"ut_fb8b84f9b3d94500b81f95b236a49934","parentId":"uts_2a43da46f9f145828b641cd71a9a04be","modified":1734024488981,"created":1734024448163,"requestId":"req_c38a7804e4c34318857a01c8100aa9f9","name":"Atualizar Item","code":"const response1 = await insomnia.send();\nexpect(response1.status).to.equal(200);","metaSortKey":-1734024448163,"_type":"unit_test"},{"_id":"ut_31df0aa53c164158a32750d13df3bff2","parentId":"uts_d0133a28c6db4d8792215b1a0342916e","modified":1734025172380,"created":1734024496197,"requestId":"req_9d9e42c7d3614167a6c1fd400eedb205","name":"Cadastrar Categoria","code":"const response1 = await insomnia.send();\nexpect(response1.status).to.equal(201);","metaSortKey":-1734024506208,"_type":"unit_test"},{"_id":"ut_b58823969214428bba8aba1b6d943cd0","parentId":"uts_d0133a28c6db4d8792215b1a0342916e","modified":1734024527489,"created":1734024500704,"requestId":"req_053445961d5248ebb0b81d7f9bed161a","name":"Listar Categoria","code":"const response1 = await insomnia.send();\nexpect(response1.status).to.equal(200);","metaSortKey":-1734024506207.5,"_type":"unit_test"},{"_id":"ut_cdee0f1fbdb84b1eb174e2ddc887cfce","parentId":"uts_d0133a28c6db4d8792215b1a0342916e","modified":1734024547544,"created":1734024502602,"requestId":"req_8345be7bab784fc2a726bdb840360608","name":"Atualizar Categoria Parcial","code":"const response1 = await insomnia.send();\nexpect(response1.status).to.equal(200);","metaSortKey":-1734024506207.25,"_type":"unit_test"},{"_id":"ut_6922bb442f544b329d8319105cbb4842","parentId":"uts_d0133a28c6db4d8792215b1a0342916e","modified":1734024555580,"created":1734024506207,"requestId":"req_f20fe92a296148bf99713581f4a0d6de","name":"Atualizar Categoria","code":"const response1 = await insomnia.send();\nexpect(response1.status).to.equal(200);","metaSortKey":-1734024506207,"_type":"unit_test"}]}